README.md
setup.cfg
setup.py
harbor/__init__.py
harbor/constant.py
harbor/main.py
harbor/utils.py
harbor/actions/__init__.py
harbor/marshallers/__init__.py
harbor/marshallers/factory.py
harbor/marshallers/mobile_marshaller.py
harbor/models/__init__.py
harbor/models/attachment.py
harbor/models/base.py
harbor/models/post.py
harbor/spider/__init__.py
harbor/spider/main.py
harbor/spider/mobile_bot.py
weibo_harbor.egg-info/PKG-INFO
weibo_harbor.egg-info/SOURCES.txt
weibo_harbor.egg-info/dependency_links.txt
weibo_harbor.egg-info/entry_points.txt
weibo_harbor.egg-info/requires.txt
weibo_harbor.egg-info/top_level.txt