Metadata-Version: 2.1
Name: weibo-harbor
Version: 0.1.1
Summary: A package to crawl, backup and export weibo content.
Home-page: https://github.com/cmsax/harbor
Author: MingshiCai
Author-email: i@unoiou.com
License: UNKNOWN
Platform: UNKNOWN
